dfwsgroup_ios/__init__.py
dfwsgroup_ios/__main__.py
dfwsgroup_ios/data/command.json
dfwsgroup_ios/ios/__init__.py
dfwsgroup_ios/ios/cli.py
dfwsgroup_ios/ios/script.py
dfwsgroup_ios-2.0.2.dist-info/LICENSE
dfwsgroup_ios-2.0.2.dist-info/METADATA
dfwsgroup_ios-2.0.2.dist-info/WHEEL
dfwsgroup_ios-2.0.2.dist-info/top_level.txt
dfwsgroup_ios-2.0.2.dist-info/RECORD
